xiaohan_mcpdemo/__init__.py
xiaohan_mcpdemo-0.1.0.dist-info/WHEEL
xiaohan_mcpdemo-0.1.0.dist-info/entry_points.txt
xiaohan_mcpdemo-0.1.0.dist-info/METADATA
xiaohan_mcpdemo-0.1.0.dist-info/RECORD
